aliyunsdkopensearch/__init__.py
aliyunsdkopensearch/endpoint.py
aliyunsdkopensearch/request/__init__.py
aliyunsdkopensearch/request/v20171225/BindESUserAnalyzerRequest.py
aliyunsdkopensearch/request/v20171225/BindEsInstanceRequest.py
aliyunsdkopensearch/request/v20171225/CompileSortScriptRequest.py
aliyunsdkopensearch/request/v20171225/CreateABTestExperimentRequest.py
aliyunsdkopensearch/request/v20171225/CreateABTestGroupRequest.py
aliyunsdkopensearch/request/v20171225/CreateABTestSceneRequest.py
aliyunsdkopensearch/request/v20171225/CreateAppGroupRequest.py
aliyunsdkopensearch/request/v20171225/CreateAppRequest.py
aliyunsdkopensearch/request/v20171225/CreateFirstRankRequest.py
aliyunsdkopensearch/request/v20171225/CreateFunctionInstanceRequest.py
aliyunsdkopensearch/request/v20171225/CreateFunctionTaskRequest.py
aliyunsdkopensearch/request/v20171225/CreateInterventionDictionaryRequest.py
aliyunsdkopensearch/request/v20171225/CreateQueryProcessorRequest.py
aliyunsdkopensearch/request/v20171225/CreateScheduledTaskRequest.py
aliyunsdkopensearch/request/v20171225/CreateSearchStrategyRequest.py
aliyunsdkopensearch/request/v20171225/CreateSecondRankRequest.py
aliyunsdkopensearch/request/v20171225/CreateSortScriptRequest.py
aliyunsdkopensearch/request/v20171225/CreateUserAnalyzerRequest.py
aliyunsdkopensearch/request/v20171225/DeleteABTestExperimentRequest.py
aliyunsdkopensearch/request/v20171225/DeleteABTestGroupRequest.py
aliyunsdkopensearch/request/v20171225/DeleteABTestSceneRequest.py
aliyunsdkopensearch/request/v20171225/DeleteFunctionInstanceRequest.py
aliyunsdkopensearch/request/v20171225/DeleteFunctionTaskRequest.py
aliyunsdkopensearch/request/v20171225/DeleteSortScriptFileRequest.py
aliyunsdkopensearch/request/v20171225/DeleteSortScriptRequest.py
aliyunsdkopensearch/request/v20171225/DescribeABTestExperimentRequest.py
aliyunsdkopensearch/request/v20171225/DescribeABTestGroupRequest.py
aliyunsdkopensearch/request/v20171225/DescribeABTestSceneRequest.py
aliyun_python_sdk_opensearch-0.12.2.dist-info/LICENSE
aliyun_python_sdk_opensearch-0.12.2.dist-info/METADATA
aliyun_python_sdk_opensearch-0.12.2.dist-info/WHEEL
aliyun_python_sdk_opensearch-0.12.2.dist-info/top_level.txt
aliyun_python_sdk_opensearch-0.12.2.dist-info/RECORD
